fitit.py
fitit-6.dist-info/METADATA
fitit-6.dist-info/WHEEL
fitit-6.dist-info/top_level.txt
fitit-6.dist-info/RECORD
